knife/__init__.py
knife/containers.py
knife/registry.py
mvadkert_knife-0.1.0.dist-info/entry_points.txt
mvadkert_knife-0.1.0.dist-info/LICENSE
mvadkert_knife-0.1.0.dist-info/WHEEL
mvadkert_knife-0.1.0.dist-info/METADATA
mvadkert_knife-0.1.0.dist-info/RECORD
