Metadata-Version: 2.1
Name: mvadkert-knife
Version: 0.1.0
Summary: Swiss army knife with various useful utilities.
License: Apache-2.0
Author: Miroslav Vadkerti
Author-email: mvadkert@redhat.com
Requires-Python: >=3.7,<4.0
Classifier: License :: OSI Approved :: Apache Software License
Classifier: Programming Language :: Python :: 3
Classifier: Programming Language :: Python :: 3.10
Classifier: Programming Language :: Python :: 3.7
Classifier: Programming Language :: Python :: 3.8
Classifier: Programming Language :: Python :: 3.9
Requires-Dist: requests (>=2.27.1,<3.0.0)
Requires-Dist: typer (>=0.4.1,<0.5.0)
